[
  {
    "id": "lru-cache",
    "title": "LRU Cache",
    "difficulty": "Medium",
    "frequency": 100,
    "acceptance": 0.45214888759813204,
    "link": "https://leetcode.com/problems/lru-cache",
    "topics": [
      "Hash Table",
      "Linked List",
      "Design",
      "Doubly-Linked List"
    ]
  },
  {
    "id": "number-of-distinct-islands",
    "title": "Number of Distinct Islands",
    "difficulty": "Medium",
    "frequency": 74.6,
    "acceptance": 0.6225556277539093,
    "link": "https://leetcode.com/problems/number-of-distinct-islands",
    "topics": [
      "Hash Table",
      "Depth-First Search",
      "Breadth-First Search",
      "Union Find",
      "Hash Function"
    ]
  },
  {
    "id": "diameter-of-binary-tree",
    "title": "Diameter of Binary Tree",
    "difficulty": "Easy",
    "frequency": 74.6,
    "acceptance": 0.6358628163246234,
    "link": "https://leetcode.com/problems/diameter-of-binary-tree",
    "topics": [
      "Tree",
      "Depth-First Search",
      "Binary Tree"
    ]
  },
  {
    "id": "word-search-ii",
    "title": "Word Search II",
    "difficulty": "Hard",
    "frequency": 74.6,
    "acceptance": 0.3732641536078909,
    "link": "https://leetcode.com/problems/word-search-ii",
    "topics": [
      "Array",
      "String",
      "Backtracking",
      "Trie",
      "Matrix"
    ]
  }
]